{
	"name": "Omniksol / Inverter",
	"description": "Monitor the amount of energy generated by your solar panels by connecting to your Omnik Inverter.",
	"run_type": "cli",
	"control_type": "none",
	"category": "appliances",
	"analytics_support": true,
	"control_support": false,
	"options": {
		"inverter_ip": {"type": "ip_address", "default": "192.168.0.0", "note": "The IP adress of your Omnik Inverter."},
		"port": {"type": "integer", "default": "8899", "min": 0, "max": 65535, "note": "The port of your Omnik Inverter (default of 8899 should work)."},
		"wifi_kit_sn": {"type": "integer", "default": "16100000", "note": "The serial number of Omnnik Inverter."}
	}
}